{
  "listing_id": "8b5f12d69b85",
  "bounding_box": {
    "left": 243.513427734375,
    "upper": 305.3277893066406,
    "right": 419.411865234375,
    "lower": 480.0,
    "image_width": 640.0,
    "image_height": 480.0,
    "score": 0.6944497227668762
  },
  "items": [
    {
      "id": "3023",
      "name": "Plate 1 x 2",
      "img_url": "https://storage.googleapis.com/brickognize-static/thumbnails-v2.6/part/3023/0.webp",
      "external_sites": [
        {
          "name": "bricklink",
          "url": "https://www.bricklink.com/v2/catalog/catalogitem.page?P=3023"
        }
      ],
      "category": "Plate",
      "type": "part",
      "score": 0.9705240726470947
    },
    {
      "id": "3023old",
      "name": "Plate 1 x 2 with Flat Bottom Pin",
      "img_url": "https://storage.googleapis.com/brickognize-static/thumbnails-v2.6/part/3023old/0.webp",
      "external_sites": [
        {
          "name": "bricklink",
          "url": "https://www.bricklink.com/v2/catalog/catalogitem.page?P=3023old"
        }
      ],
      "category": "Plate",
      "type": "part",
      "score": 0.9124746322631836
    }
  ]
}