{
  "listing_id": "d011e284b670",
  "bounding_box": {
    "left": 41.11948776245117,
    "upper": 281.7672424316406,
    "right": 150.6322021484375,
    "lower": 406.010498046875,
    "image_width": 640.0,
    "image_height": 480.0,
    "score": 0.6870391964912415
  },
  "items": [
    {
      "id": "15712",
      "name": "Tile, Modified 1 x 1 with Open O Clip",
      "img_url": "https://storage.googleapis.com/brickognize-static/thumbnails-v2.6/part/15712/0.webp",
      "external_sites": [
        {
          "name": "bricklink",
          "url": "https://www.bricklink.com/v2/catalog/catalogitem.page?P=15712"
        }
      ],
      "category": "Tile, Modified",
      "type": "part",
      "score": 0.9817837476730347
    }
  ]
}